django_db_locking-2.0.4.dist-info/DESCRIPTION.rst
django_db_locking-2.0.4.dist-info/METADATA
django_db_locking-2.0.4.dist-info/RECORD
django_db_locking-2.0.4.dist-info/WHEEL
django_db_locking-2.0.4.dist-info/metadata.json
django_db_locking-2.0.4.dist-info/top_level.txt
locking/__init__.py
locking/admin.py
locking/exceptions.py
locking/models.py
locking/tasks.py
locking/tests.py
locking/views.py
locking/migrations/0001_initial.py
locking/migrations/0001_squashed_0007_auto_20171004_0900.py
locking/migrations/0002_auto_20171004_1309.py
locking/migrations/0002_rename.py
locking/migrations/0003_optimize_queries.py
locking/migrations/0004_auto_20151115_0703.py
locking/migrations/0004_auto_20160907_0942.py
locking/migrations/0005_merge_20170504_1024.py
locking/migrations/0006_auto_20170609_1342.py
locking/migrations/0007_auto_20171004_0900.py
locking/migrations/__init__.py
test_project/__init__.py
test_project/manage.py
test_project/settings.py
test_project/urls.py
test_project/wsgi.py
