Metadata-Version: 2.0
Name: django-db-locking
Version: 2.0.4
Summary: Database locking
Home-page: https://github.com/vikingco/django-db-locking/
Author: VikingCo
Author-email: operations@unleashed.be
License: BSD
Platform: UNKNOWN
Classifier: Intended Audience :: Developers
Classifier: Programming Language :: Python
Classifier: Programming Language :: Python :: 2.7
Classifier: Programming Language :: Python :: 3
Classifier: Programming Language :: Python :: 3.6
Classifier: Operating System :: OS Independent
Classifier: Environment :: Web Environment
Classifier: Framework :: Django
Requires-Dist: Django
Provides-Extra: celery
Requires-Dist: celery; extra == 'celery'
